polyaxon_gpustat.py
polyaxon_gpustat-0.3.4.dist-info/DESCRIPTION.rst
polyaxon_gpustat-0.3.4.dist-info/METADATA
polyaxon_gpustat-0.3.4.dist-info/RECORD
polyaxon_gpustat-0.3.4.dist-info/WHEEL
polyaxon_gpustat-0.3.4.dist-info/metadata.json
polyaxon_gpustat-0.3.4.dist-info/top_level.txt
