Metadata-Version: 2.0
Name: polyaxon-gpustat
Version: 0.3.4
Summary: An utility to monitor NVIDIA GPU status and usage
Home-page: https://github.com/polyaxon/polyaxon-gpustat
Author: Mourad Mourafiq
Author-email: mourad@polyaxon.com
License: MIT
Keywords: nvidia-smi gpu cuda monitoring gpustat
Platform: UNKNOWN
Classifier: Development Status :: 3 - Alpha
Classifier: License :: OSI Approved :: MIT License
Classifier: Operating System :: POSIX :: Linux
Classifier: Programming Language :: Python :: 2.7
Classifier: Programming Language :: Python :: 3
Classifier: Topic :: System :: Monitoring
Requires-Dist: nvidia-ml-py3 (==7.352.0)
Requires-Dist: psutil (==5.4.7)
Requires-Dist: blessings (==1.6.1)
Provides-Extra: test
Requires-Dist: mock (==2.0.0); extra == 'test'
Requires-Dist: pytest (==3.7.0); extra == 'test'
